deepac/__init__.py
deepac/__main__.py
deepac/builtin_loading.py
deepac/command_line.py
deepac/convert.py
deepac/nn_train.py
deepac/predict.py
deepac/preproc.py
deepac/tformers.py
deepac/utils.py
deepac/builtin/config/nn-img-rapid-cnn.ini
deepac/builtin/config/nn-img-sensitive-lstm.ini
deepac/builtin/config/nn-resnet18.ini
deepac/builtin/config_templates/eval_config.ini
deepac/builtin/config_templates/eval_ens_config.ini
deepac/builtin/config_templates/eval_species_config.ini
deepac/builtin/config_templates/preproc_config.ini
deepac/builtin/weights/nn-img-rapid-cnn.h5
deepac/builtin/weights/nn-img-sensitive-lstm.h5
deepac/eval/__init__.py
deepac/eval/eval.py
deepac/eval/eval_ens.py
deepac/eval/eval_species.py
deepac/explain/IC_from_transfac.py
deepac/explain/__init__.py
deepac/explain/command_line.py
deepac/explain/deepbind_scores.py
deepac/explain/fasta2transfac.py
deepac/explain/filter_contribs.py
deepac/explain/filter_ranking.py
deepac/explain/motif_comparison.py
deepac/explain/rf_sizes.py
deepac/explain/tests.py
deepac/explain/weblogos.py
deepac/explain/weblogos_extended.py
deepac/gwpa/__init__.py
deepac/gwpa/command_line.py
deepac/gwpa/filter_activations.py
deepac/gwpa/filter_enrichment.py
deepac/gwpa/fragment_genomes.py
deepac/gwpa/gene_ranking.py
deepac/gwpa/genome_pathogenicity.py
deepac/gwpa/nt_contribs.py
deepac/gwpa/tests.py
deepac/tests/__init__.py
deepac/tests/datagen.py
deepac/tests/rctest.py
deepac/tests/testcalls.py
deepac/tests/configs/eval-test.ini
deepac/tests/configs/eval_ens-test.ini
deepac/tests/configs/eval_species-test.ini
deepac/tests/configs/nn-test-L.ini
deepac/tests/configs/nn-test.ini
deepac/tests/configs/preproc-train-multi.ini
deepac/tests/configs/preproc-train.ini
deepac/tests/configs/preproc-val-multi.ini
deepac/tests/configs/preproc-val.ini
deepac-0.14.1.dist-info/LICENSE
deepac-0.14.1.dist-info/METADATA
deepac-0.14.1.dist-info/WHEEL
deepac-0.14.1.dist-info/entry_points.txt
deepac-0.14.1.dist-info/top_level.txt
deepac-0.14.1.dist-info/RECORD
