Metadata-Version: 2.1
Name: deepac
Version: 0.14.1
Summary: Predicting pathogenic potentials of novel DNA with reverse-complement neural networks.
Home-page: https://gitlab.com/dacs-hpi/deepac
Author: Jakub Bartoszewicz
Author-email: jakub.bartoszewicz@hpi.de
License: MIT
Keywords: deep learning DNA sequencing synthetic biology pathogenicity prediction
Platform: UNKNOWN
Classifier: Development Status :: 4 - Beta
Classifier: License :: OSI Approved :: MIT License
Classifier: Programming Language :: Python :: 3
Classifier: Programming Language :: Python :: 3.6
Classifier: Programming Language :: Python :: 3.7
Classifier: Programming Language :: Python :: 3.8
Classifier: Programming Language :: Python :: 3.9
Classifier: Topic :: Scientific/Engineering :: Bio-Informatics
Requires-Python: >=3
Requires-Dist: tensorflow (>=2.1.2)
Requires-Dist: biopython (>=1.78)
Requires-Dist: scikit-learn (>=0.22.1)
Requires-Dist: matplotlib (>=3.1.3)
Requires-Dist: numpy (>=1.17)
Requires-Dist: h5py (>=2.10)
Requires-Dist: psutil (>=5.6.7)
Requires-Dist: wget (>=3.2)
Requires-Dist: requests (>=2.24)
Requires-Dist: shap (>=0.35)
Requires-Dist: weblogo (>=3.7)
Requires-Dist: pybedtools (>=0.8.1)
Requires-Dist: statsmodels (>=0.11.0)
Requires-Dist: seaborn (>=0.11)
Requires-Dist: termcolor (>=1.1.0)
Requires-Dist: tqdm (>=4.49)
